guilite/__init__.py
guilite/app/__init__.py
guilite/app/__version__.py
guilite/app/routes.py
guilite/app/webapp.py
guilite/app/static/main.js
guilite/app/static/style.css
guilite/app/templates/index.html
guilite/examples/__init__.py
guilite/examples/add_and_multiply_simulators.py
guilite/examples/demo_engine.py
guilite/examples/demo_simulator.py
guilite/examples/engine_report_demo.py
guilite/examples/mysimulator.py
guilite/examples/run_webapp.py
guilite/reportgenerator/__init__.py
guilite/reportgenerator/__version__.py
guilite/reportgenerator/engine.py
guilite/reportgenerator/htmlrenderer.py
guilite/reportgenerator/simulatorapp.py
guilite/reportgenerator/simulatorbase.py
guilite/reportgenerator/templates/index.html
guilite/reportgenerator/templates/model_table.html
guilite-0.1.2.dist-info/licenses/LICENSE
guilite-0.1.2.dist-info/METADATA
guilite-0.1.2.dist-info/WHEEL
guilite-0.1.2.dist-info/top_level.txt
guilite-0.1.2.dist-info/RECORD
