Metadata-Version: 2.4
Name: guilite
Version: 0.1.2
Summary: A lightweight, extensible Python library for simulation, reporting, and web-based input/output. Includes automatic web UI, report generation, and support for custom simulators.
Author: Kjell Kolsaker
License: MIT License
Project-URL: Homepage, https://github.com/kjelkols/guilite
Project-URL: Bug Tracker, https://github.com/kjelkols/guilite/issues
Classifier: Programming Language :: Python :: 3
Classifier: License :: OSI Approved :: MIT License
Classifier: Operating System :: OS Independent
Requires-Python: >=3.8
License-File: LICENSE
Requires-Dist: Flask
Requires-Dist: pydantic>=1.10
Requires-Dist: jinja2
Dynamic: license-file
Dynamic: requires-python
